impyrialaremou/__init__.py
impyrialaremou/utils.py
impyrialaremou/length/__init__.py
impyrialaremou/length/api.py
impyrialaremou/length/core.py
impyrialaremou/weight/__init__.py
impyrialaremou/weight/api.py
impyrialaremou/weight/core.py
impyrialaremou-0.3.0.dist-info/LICENSE
impyrialaremou-0.3.0.dist-info/METADATA
impyrialaremou-0.3.0.dist-info/WHEEL
impyrialaremou-0.3.0.dist-info/top_level.txt
impyrialaremou-0.3.0.dist-info/RECORD
